{"cameraMode":{"drawMode":0,"name":"Shaded","section":"Shading Mode"},"sceneLighting":true,"audioPlay":false,"sceneViewState":{"showFog":true,"showMaterialUpdate":false,"showSkybox":true,"showFlares":true,"showImageEffects":true,"showParticleSystems":true},"in2DMode":false,"pivot":{"x":-4069.531494140625,"y":1.4142969846725464,"z":-3553.25439453125},"rotation":{"x":-0.018270395696163179,"y":-0.9421527981758118,"z":0.3306266963481903,"w":-0.05206359922885895},"size":11810.447265625,"orthographic":false}